MANIFEST.in
README.txt
setup.py
windmill/__init__.py
windmill.egg-info/PKG-INFO
windmill.egg-info/SOURCES.txt
windmill.egg-info/dependency_links.txt
windmill.egg-info/entry_points.txt
windmill.egg-info/top_level.txt
windmill/authoring/__init__.py
windmill/authoring/djangotest.py
windmill/authoring/frame.py
windmill/authoring/nose_plugin.py
windmill/authoring/transforms.py
windmill/authoring/unit.py
windmill/bin/__init__.py
windmill/bin/admin_lib.py
windmill/bin/admin_options.py
windmill/bin/json2python.py
windmill/bin/shell_objects.py
windmill/bin/windmill_bin.py
windmill/browser/__init__.py
windmill/browser/cert8.db
windmill/browser/chrome.py
windmill/browser/ie.py
windmill/browser/killableprocess.py
windmill/browser/safari.py
windmill/browser/winprocess.py
windmill/conf/__init__.py
windmill/conf/global_settings.py
windmill/conf/local_settings.py
windmill/dep/__init__.py
windmill/dep/_uuid.py
windmill/dep/_functest/__init__.py
windmill/dep/_functest/bin.py
windmill/dep/_functest/collector.py
windmill/dep/_functest/formatter.py
windmill/dep/_functest/frame.py
windmill/dep/_functest/global_settings.py
windmill/dep/_functest/reports.py
windmill/dep/_functest/runner.py
windmill/dep/_mozrunner/__init__.py
windmill/dep/_mozrunner/getmoz.py
windmill/dep/_mozrunner/global_settings.py
windmill/dep/_mozrunner/install.py
windmill/dep/_mozrunner/killableprocess.py
windmill/dep/_mozrunner/runner.py
windmill/dep/_mozrunner/termutil.py
windmill/dep/_mozrunner/winprocess.py
windmill/dep/_simplejson/__init__.py
windmill/dep/_simplejson/decoder.py
windmill/dep/_simplejson/encoder.py
windmill/dep/_simplejson/scanner.py
windmill/dep/_simplejson/tool.py
windmill/dep/_simplejson/tests/__init__.py
windmill/dep/_simplejson/tests/test_check_circular.py
windmill/dep/_simplejson/tests/test_decode.py
windmill/dep/_simplejson/tests/test_default.py
windmill/dep/_simplejson/tests/test_dump.py
windmill/dep/_simplejson/tests/test_encode_basestring_ascii.py
windmill/dep/_simplejson/tests/test_fail.py
windmill/dep/_simplejson/tests/test_float.py
windmill/dep/_simplejson/tests/test_indent.py
windmill/dep/_simplejson/tests/test_pass1.py
