Metadata-Version: 1.0
Name: windmill
Version: 1.5
Summary: Web testing framework intended for complete automation of user interface testing, with strong test debugging and recording capabilities.
Home-page: http://www.getwindmill.com/
Author: OSAF, Mikeal Rogers, Adam Christian
Author-email: windmill-dev@googlegroups.com
License: http://www.apache.org/licenses/LICENSE-2.0
Platform: Any
Classifier: Development Status :: 4 - Beta
Classifier: Environment :: Console
Classifier: Intended Audience :: Developers
Classifier: License :: OSI Approved :: Apache Software License
Classifier: Operating System :: OS Independent
Classifier: Topic :: Software Development :: Libraries :: Python Modules
